chord_progression_network/__init__.py
chord_progression_network/chord_progression_network.py
chord_progression_network-0.2.11.dist-info/licenses/LICENSE
chord_progression_network-0.2.11.dist-info/METADATA
chord_progression_network-0.2.11.dist-info/WHEEL
chord_progression_network-0.2.11.dist-info/top_level.txt
chord_progression_network-0.2.11.dist-info/RECORD
