Metadata-Version: 2.4
Name: chord_progression_network
Version: 0.2.11
Summary: Network transition chord progressions
Author-email: Gene Boggs <gene.boggs@gmail.com>
License:                     GNU GENERAL PUBLIC LICENSE
Project-URL: Homepage, https://github.com/ology/python-chord-progression-network
Project-URL: Repository, https://github.com/ology/python-chord-progression-network.git
Project-URL: Issues, https://github.com/ology/python-chord-progression-network/issues
Classifier: Development Status :: 2 - Pre-Alpha
Classifier: Programming Language :: Python
Classifier: Programming Language :: Python :: 3
Classifier: Programming Language :: Python :: 3.9
Classifier: Programming Language :: Python :: 3.10
Classifier: Programming Language :: Python :: 3.11
Classifier: Programming Language :: Python :: 3.12
Requires-Python: >=3.9
License-File: LICENSE
Requires-Dist: networkx
Requires-Dist: musical_scales
Requires-Dist: pychord
Dynamic: license-file
